LICENSE
MANIFEST.in
README.md
requirements.txt
setup.cfg
setup.py
zen_document_parser/__init__.py
zen_document_parser/base.py
zen_document_parser/exceptions.py
zen_document_parser.egg-info/PKG-INFO
zen_document_parser.egg-info/SOURCES.txt
zen_document_parser.egg-info/dependency_links.txt
zen_document_parser.egg-info/requires.txt
zen_document_parser.egg-info/top_level.txt
zen_document_parser/itr/__init__.py
zen_document_parser/itr/itr.py
zen_document_parser/itr/schema.py