Metadata-Version: 1.1
Name: zen-document-parser
Version: 0.11
Summary: A library for parsing various government documents as well as general PDFs
Home-page: https://github.com/loanzen/zen_document_parser
Author: Loanzen
Author-email: hello@loanzen.in
License: MIT
Keywords: pdf parse itr documents
Platform: UNKNOWN
Classifier: Development Status :: 4 - Beta
Classifier: Intended Audience :: Developers
Classifier: Topic :: Software Development :: Libraries
Classifier: Topic :: Utilities
Classifier: License :: OSI Approved :: MIT License
Classifier: Programming Language :: Python :: 2
Classifier: Programming Language :: Python :: 2.6
Classifier: Programming Language :: Python :: 2.7
Classifier: Programming Language :: Python :: 3
Classifier: Programming Language :: Python :: 3.3
Classifier: Programming Language :: Python :: 3.4
Classifier: Programming Language :: Python :: 3.5
